systemctl_init.py
systemctl_init-0.1.0.dist-info/METADATA
systemctl_init-0.1.0.dist-info/WHEEL
systemctl_init-0.1.0.dist-info/RECORD
